libvxe_py/__init__.py
libvxe_py/util.py
libvxe_py-0.2.dist-info/METADATA
libvxe_py-0.2.dist-info/RECORD
libvxe_py-0.2.dist-info/WHEEL
libvxe_py-0.2.dist-info/top_level.txt
